socialysis/SAMPLE_DATA.pkl
socialysis/SW.py
socialysis/__init__.py
socialysis/common_plots.py
socialysis/emoji.py
socialysis/get_df.py
socialysis/media.py
socialysis/plot_helper.py
socialysis/sample_meta_data.json
socialysis/share.py
socialysis/socialysis.py
socialysis/special_plots.py
socialysis/sw.txt
socialysis/utils.py
socialysis/words.py
socialysis/words_helper.py
socialysis/stickers_used/106294536_1000531610402543_5152096205522142045_n_1000531603735877.png
socialysis/stickers_used/14130009_1775288522711852_127155195_n_1775288509378520.png
socialysis/stickers_used/16684960_1825511351057032_8015068311945478144_n_1825511347723699.png
socialysis/stickers_used/17527812_1652591011433966_4391041969200037888_n_1652591004767300.png
socialysis/stickers_used/39178562_1505197616293642_5411344281094848512_n_369239263222822.png
socialysis/stickers_used/46949788_1074619346032831_6110986696902311936_n_383649078463198.png
socialysis/stickers_used/47231424_2005270362889541_5537841470372839424_n_657503044332953.png
socialysis/stickers_used/48587739_1881522991957829_7012074305936687104_n_832506750192797.png
socialysis/stickers_used/49166664_522366711599821_6802607359341363200_n_255662728270222.png
socialysis/stickers_used/69086425_916982675311781_1405267837022371840_n_272549366421785.png
socialysis/stickers_used/851582_369239386556143_1497813874_n_369239383222810.png
socialysis/stickers_used/851587_369239346556147_162929011_n_369239343222814.png
socialysis-0.1.0.dist-info/LICENSE
socialysis-0.1.0.dist-info/METADATA
socialysis-0.1.0.dist-info/WHEEL
socialysis-0.1.0.dist-info/top_level.txt
socialysis-0.1.0.dist-info/RECORD
