Metadata-Version: 2.1
Name: socialysis
Version: 0.1.0
Summary: Tool for analyzing and extracting insights from Facebook Messenger conversations
Home-page: https://github.com/abdulrahmankhayal/socialysis
Author: Abdul-Rahman Khayyal
License: MIT
Keywords: Facebook Messenger Analysis
Platform: UNKNOWN
Classifier: Intended Audience :: Developers
Classifier: Programming Language :: Python
Classifier: Programming Language :: Python :: 3
Classifier: Programming Language :: Python :: 3.8
Classifier: Programming Language :: Python :: 3.9
Classifier: Programming Language :: Python :: 3.10
Classifier: Operating System :: OS Independent
Requires-Python: >=3.8
License-File: LICENSE
Requires-Dist: arabic-reshaper
Requires-Dist: emoji
Requires-Dist: imojify
Requires-Dist: librosa
Requires-Dist: matplotlib (>=3.5.1)
Requires-Dist: numpy
Requires-Dist: opencv-python
Requires-Dist: pandas (>=1.4.1)
Requires-Dist: Pillow
Requires-Dist: python-bidi
Requires-Dist: regex
Requires-Dist: tldextract
Requires-Dist: tqdm
Requires-Dist: wordcloud
